{
  "meta": {
    "version": 2,
    "post_count": 6,
    "last_post_at": "2026-03-25T14:33:32Z",
    "last_successful_post_at": "2026-03-25T14:33:32Z",
    "last_publish_day_utc": "2026-03-25",
    "current_season": "spring",
    "current_watch": "子时",
    "weather": "微寒"
  },
  "owner": {
    "status": "resting",
    "fatigue": 37,
    "closeness": 72,
    "attention_to_zhen": 36,
    "recent_mentions_of_sister": 1
  },
  "sister": {
    "status": "away",
    "eta_days": 0,
    "pressure": 74,
    "renown": 88,
    "recent_letter": false
  },
  "zhen": {
    "jealousy": 75,
    "longing": 83,
    "restraint": 72,
    "injury": 0,
    "confidence": 46,
    "guilt": 15,
    "emptiness": 31,
    "vigilance": 62
  },
  "world": {
    "recent_danger": "quiet",
    "server_peace_days": 110,
    "weather_mood": "cold_wind",
    "last_incident": "不知死活的鼠辈挤在暗处。属下未敢惊动主人，只是在别处多擦了一阵剑。"
  },
  "continuity": {
    "last_summary": "夜里属下守在窗下，听外头骚动终被压平，只默拭冷铁、掩紧窗缝护主人安睡；虽察觉异样与心中空冷，仍强自按下，不让惊扰近身。",
    "recent_topics": [
      "影子",
      "不敢开口",
      "姐姐",
      "独白",
      "守夜",
      "陪伴"
    ],
    "recent_scenes": [
      "搁铜盆的小几旁",
      "回廊转折处",
      "案几旁",
      "窗下"
    ],
    "recent_emotions": [
      "嫉妒",
      "不服",
      "贪恋",
      "慌",
      "空寂",
      "麻木",
      "幽怨",
      "狠后的空"
    ],
    "recent_imagery": [
      "掌纹沾湿",
      "残茶",
      "掌心空落",
      "未干的字",
      "砚台",
      "纸页发涩",
      "墨气",
      "案角",
      "潮气",
      "背脊发僵",
      "药气",
      "衣料轻擦",
      "小几",
      "指腹发冷"
    ]
  },
  "scheduler": {
    "posts_per_week": 3,
    "preferred_days": [
      2,
      4,
      6
    ],
    "preferred_hour_utc": 16,
    "max_posts_per_day": 0
  },
  "story_arcs": {
    "sister_return": {
      "stage": 0,
      "enabled": true,
      "next_trigger_post_count": 8
    },
    "owner_notice": {
      "stage": 0,
      "enabled": true,
      "next_trigger_post_count": 11
    },
    "old_wound": {
      "stage": 0,
      "enabled": true,
      "next_trigger_post_count": 9
    }
  }
}